deci_client/__init__.py
deci_client/client.py
deci_client/deci_api/__init__.py
deci_client/deci_api/api_client.py
deci_client/deci_api/configuration.py
deci_client/deci_api/exceptions.py
deci_client/deci_api/rest.py
deci_client/deci_api/api/__init__.py
deci_client/deci_api/api/companies_api.py
deci_client/deci_api/api/platform_api.py
deci_client/deci_api/api/settings_api.py
deci_client/deci_api/api/version_api.py
deci_client/deci_api/client/__init__.py
deci_client/deci_api/client/deci_platform_client.py
deci_client/deci_api/models/__init__.py
deci_client/deci_api/models/accuracy_metric.py
deci_client/deci_api/models/accuracy_metric_key.py
deci_client/deci_api/models/accuracy_metric_type.py
deci_client/deci_api/models/accuracy_metrics_schema_response.py
deci_client/deci_api/models/activity_event_name.py
deci_client/deci_api/models/add_model_response.py
deci_client/deci_api/models/api_response.py
deci_client/deci_api/models/api_response_add_model_response.py
deci_client/deci_api/models/api_response_baseline_model_response_metadata.py
deci_client/deci_api/models/api_response_benchmark_request_metadata.py
deci_client/deci_api/models/api_response_delete_model_response.py
deci_client/deci_api/models/api_response_dict_deci_infra_data_types_enum_deep_learning_task_deep_learning_task_api_common_data_types_global_configuration_data_types_accuracy_metrics_schema_response.py
deci_client/deci_api/models/api_response_dict_deci_infra_data_types_enum_deep_learning_task_deep_learning_task_list_deci_infra_data_types_enum_models_enums_accuracy_metric_key.py
deci_client/deci_api/models/api_response_dict_deci_infra_data_types_enum_users_enums_activity_event_name_int.py
deci_client/deci_api/models/api_response_dict_infra_data_types_enum_deep_learning_task_deep_learning_task_list_infra_data_types_enum_models_enums_accuracy_metric_key.py
deci_client/deci_api/models/api_response_dict_infra_data_types_enum_users_enums_activity_event_name_int.py
deci_client-1.38.1.dist-info/METADATA
deci_client-1.38.1.dist-info/WHEEL
deci_client-1.38.1.dist-info/top_level.txt
deci_client-1.38.1.dist-info/RECORD
